wireviz_fences/__init__.py
wireviz_fences-0.1.0.dist-info/LICENSE
wireviz_fences-0.1.0.dist-info/METADATA
wireviz_fences-0.1.0.dist-info/WHEEL
wireviz_fences-0.1.0.dist-info/RECORD
